pars_sms/__init__.py
pars_sms/sms.py
py_persian_sms-0.0.3.dist-info/LICENSE
py_persian_sms-0.0.3.dist-info/METADATA
py_persian_sms-0.0.3.dist-info/WHEEL
py_persian_sms-0.0.3.dist-info/top_level.txt
py_persian_sms-0.0.3.dist-info/RECORD
