Metadata-Version: 2.1
Name: py-persian-sms
Version: 0.0.3
Summary: A Python library for sending SMS via sms.ir API
Home-page: https://github.com/nashviamir/py-persian-sms
Author: Amirhossein Nashvi
Author-email: <amirhosseinnashvi@gmail.com>
License: UNKNOWN
Keywords: sms.ir,sms,python-sms.ir
Platform: UNKNOWN
Classifier: Development Status :: 1 - Planning
Classifier: Intended Audience :: Developers
Classifier: Programming Language :: Python :: 3
Classifier: Operating System :: Unix
Classifier: Operating System :: MacOS :: MacOS X
Classifier: Operating System :: Microsoft :: Windows
License-File: LICENSE
Requires-Dist: requests
